ngstrefftz/__init__.py
ngstrefftz/__init__.pyi
ngstrefftz/ngstrefftz.so
ngstrefftz-0.3.2505.dist-info/METADATA
ngstrefftz-0.3.2505.dist-info/WHEEL
ngstrefftz-0.3.2505.dist-info/licenses/LICENSE
ngstrefftz-0.3.2505.dist-info/RECORD
