Metadata-Version: 2.2
Name: ngstrefftz
Version: 0.3.2505
Summary: NGSTrefftz is an add-on to NGSolve for Trefftz methods.
Author-Email: Paul Stocker <paul.stocker@univie.ac.at>
Classifier: License :: OSI Approved :: GNU Lesser General Public License v3 (LGPLv3)
Project-URL: Documentation, https://paulst.github.io/NGSTrefftz
Project-URL: Repository, https://github.com/PaulSt/ngstrefftz
Requires-Python: >=3.9
Requires-Dist: ngsolve==6.2.2504
